math_and_points/__init__.py
math_and_points/math_basic.py
math_and_points/points.py
math_and_points-0.1.3.dist-info/METADATA
math_and_points-0.1.3.dist-info/WHEEL
math_and_points-0.1.3.dist-info/top_level.txt
math_and_points-0.1.3.dist-info/RECORD
