Metadata-Version: 2.1
Name: math_and_points
Version: 0.1.3
Summary: Operaciones básicas con dos o más números y, por otra parte, operaciones con puntos en dos dimensiones.
Home-page: 
Author: Lucas Gongora
